<?xml version='1.0' encoding='UTF-8'?>
<com.cloudbees.plugins.credentials.SystemCredentialsProvider plugin="credentials@2.1.16">
  <domainCredentialsMap class="hudson.util.CopyOnWriteMap$Hash">
    <entry>
      <com.cloudbees.plugins.credentials.domains.Domain>
        <specifications/>
      </com.cloudbees.plugins.credentials.domains.Domain>
      <java.util.concurrent.CopyOnWriteArrayList>
        <com.cloudbees.jenkins.plugins.sshcredentials.impl.BasicSSHUserPrivateKey plugin="ssh-credentials@1.13">
          <scope>GLOBAL</scope>
          <id>e241885f-ab81-45d5-bc8b-f51ca4e519f2</id>
          <description></description>
          <username></username>
          <privateKeySource class="com.cloudbees.jenkins.plugins.sshcredentials.impl.BasicSSHUserPrivateKey$UsersPrivateKeySource"/>
        </com.cloudbees.jenkins.plugins.sshcredentials.impl.BasicSSHUserPrivateKey>
        <com.dabsquared.gitlabjenkins.connection.GitLabApiTokenImpl plugin="gitlab-plugin@1.5.2">
          <scope>GLOBAL</scope>
          <id>8bea63bd-2e1e-4302-ac22-0fc97dcc3045</id>
          <description></description>
          <apiToken>{AQAAABAAAAAg4zA+HQjFsxykJhaj1sCsTQ3gSqRbEQUNNx5fSCWwknKjv5Ozqk7gmcNlcHRMFmqr}</apiToken>
        </com.dabsquared.gitlabjenkins.connection.GitLabApiTokenImpl>
        <com.cloudbees.plugins.credentials.impl.UsernamePasswordCredentialsImpl>
          <scope>GLOBAL</scope>
          <id>11fe95c0-8913-4ea2-92aa-cddc32b3a64d</id>
          <description></description>
          <username>admin</username>
          <password>{AQAAABAAAAAgrCk/vSqpvrE9tF/QSpGNayEarETdwMoQPx9o2r9loh+drR9S1zOqc/zxN3Pfsv+S}</password>
        </com.cloudbees.plugins.credentials.impl.UsernamePasswordCredentialsImpl>
        <com.cloudbees.plugins.credentials.impl.UsernamePasswordCredentialsImpl>
          <scope>GLOBAL</scope>
          <id>589bc883-6863-4852-b7d6-b87ed5e047f3</id>
          <description></description>
          <username></username>
          <password>{AQAAABAAAAAgABBLJIgoj3fo2QlDdHScItYosy7wMO4wQS8MktlCiRGU/lRjcXUZ/qheaIAyhlVa}</password>
        </com.cloudbees.plugins.credentials.impl.UsernamePasswordCredentialsImpl>
        <com.cloudbees.plugins.credentials.impl.UsernamePasswordCredentialsImpl>
          <scope>GLOBAL</scope>
          <id>07353eb0-ee7c-486e-b8cb-6a305e084e6a</id>
          <description></description>
          <username></username>
          <password>{AQAAABAAAAAgZZGydmWwZS0IsrfdCkPqTHPgNxWPklKS3sc4cQfe9szgB6Blmszci2vTUww3xR4l}</password>
        </com.cloudbees.plugins.credentials.impl.UsernamePasswordCredentialsImpl>
      </java.util.concurrent.CopyOnWriteArrayList>
    </entry>
  </domainCredentialsMap>
</com.cloudbees.plugins.credentials.SystemCredentialsProvider>